src/notification_center/__init__.py
src/notification_center/__main__.py
src/notification_center/notification_center.py
src/notification_center/sqs_services.py
notification_center_ma-0.0.1.dist-info/LICENSE
notification_center_ma-0.0.1.dist-info/METADATA
notification_center_ma-0.0.1.dist-info/WHEEL
notification_center_ma-0.0.1.dist-info/entry_points.txt
notification_center_ma-0.0.1.dist-info/top_level.txt
notification_center_ma-0.0.1.dist-info/RECORD
