Metadata-Version: 2.1
Name: notification-center-ma
Version: 0.0.1
Summary: A package for sending notifications internally for MobileArts
Author: Fatima Medlij
Author-email: Fatima Medlij <medlijfatima@gmail.com>
License: MIT License
Keywords: notification,messaging,communication
Classifier: License :: OSI Approved :: MIT License
Classifier: Programming Language :: Python
Classifier: Programming Language :: Python :: 3
Requires-Python: >=3.9
License-File: LICENSE
Requires-Dist: email-validator
Requires-Dist: sqs-services
Requires-Dist: boto3
Requires-Dist: urllib3
Requires-Dist: botocore
Requires-Dist: python-dotenv
